tresto/__init__.py
tresto/tresto.py
tresto-0.1.2.dist-info/METADATA
tresto-0.1.2.dist-info/WHEEL
tresto-0.1.2.dist-info/top_level.txt
tresto-0.1.2.dist-info/RECORD
