Metadata-Version: 2.1
Name: tresto
Version: 0.1.2
Summary: Python unit testing integrated with Trello, providing visualization of project status, ideal for test-driven development
Home-page: https://github.com/buanzo/tresto
Author: Arturo 'Buanzo' Busleiman
Author-email: buanzo@buanzo.com.ar
Classifier: Programming Language :: Python :: 3
Classifier: License :: OSI Approved :: MIT License
Classifier: Operating System :: OS Independent
Requires-Python: >=3.6
Requires-Dist: py-trello
